[
    {
        "type": "message",
        "subtype": "channel_join",
        "ts": "1648803679.172689",
        "user": "U039RCZ4E04",
        "text": "<@U039RCZ4E04>さんがチャンネルに参加しました"
    },
    {
        "type": "message",
        "subtype": "channel_join",
        "ts": "1648804163.090929",
        "user": "U03A1N54PJM",
        "text": "<@U03A1N54PJM>さんがチャンネルに参加しました"
    },
    {
        "type": "message",
        "subtype": "channel_join",
        "ts": "1648804452.327169",
        "user": "U039P4NSKM1",
        "text": "<@U039P4NSKM1>さんがチャンネルに参加しました"
    },
    {
        "type": "message",
        "subtype": "channel_join",
        "ts": "1648804787.642829",
        "user": "U039L92GA3X",
        "text": "<@U039L92GA3X>さんがチャンネルに参加しました"
    },
    {
        "type": "message",
        "subtype": "channel_join",
        "ts": "1648805894.195299",
        "user": "U03A1S6RAF3",
        "text": "<@U03A1S6RAF3>さんがチャンネルに参加しました"
    },
    {
        "type": "message",
        "subtype": "channel_join",
        "ts": "1648806175.074919",
        "user": "U039RJU3V36",
        "text": "<@U039RJU3V36>さんがチャンネルに参加しました"
    },
    {
        "type": "message",
        "subtype": "channel_join",
        "ts": "1648806897.462789",
        "user": "U039PA9J5JP",
        "text": "<@U039PA9J5JP>さんがチャンネルに参加しました"
    },
    {
        "type": "message",
        "subtype": "channel_join",
        "ts": "1648808211.775809",
        "user": "U039LGX8MN1",
        "text": "<@U039LGX8MN1>さんがチャンネルに参加しました"
    },
    {
        "type": "message",
        "subtype": "channel_join",
        "ts": "1648811566.143759",
        "user": "U039H10MUTY",
        "text": "<@U039H10MUTY>さんがチャンネルに参加しました"
    },
    {
        "type": "message",
        "subtype": "channel_join",
        "ts": "1648878260.953729",
        "user": "U039M3UAXFG",
        "text": "<@U039M3UAXFG>さんがチャンネルに参加しました"
    },
    {
        "type": "message",
        "subtype": "channel_join",
        "ts": "1648879754.407689",
        "user": "U039D5XVCJ3",
        "text": "<@U039D5XVCJ3>さんがチャンネルに参加しました"
    }
]